src/__init__.py
src/Color_Light/__init__.py
src/Color_Light/brightness_linear.py
src/Color_Light/exposure_contrast.py
src/Color_Light/exposure_contrastdng.py
src/Color_Light/metadata.py
src/Color_Light/whitesandblacks.py
src/historgram_filters/__init__.py
src/historgram_filters/noise.py
src/historgram_filters/sharpening.py
src/kernelbased_spatial/Texture.py
src/kernelbased_spatial/__init__.py
src/kernelbased_spatial/highlightsandshadow.py
src/utils/__init__.py
utils/__init__.py
MobilTelesco-0.1.dist-info/LICENSE
MobilTelesco-0.1.dist-info/METADATA
MobilTelesco-0.1.dist-info/WHEEL
MobilTelesco-0.1.dist-info/top_level.txt
MobilTelesco-0.1.dist-info/RECORD
