Metadata-Version: 2.1
Name: MobilTelesco
Version: 0.1
License-File: LICENSE
Requires-Dist: numpy
Requires-Dist: opencv-python
Requires-Dist: tifffile
Requires-Dist: pytest
Requires-Dist: imageio
Requires-Dist: pyexiv2
Requires-Dist: pandas
